LICENSE
setup.py
ebookonix/__init__.py
ebookonix/__main__.py
ebookonix.egg-info/PKG-INFO
ebookonix.egg-info/SOURCES.txt
ebookonix.egg-info/dependency_links.txt
ebookonix.egg-info/top_level.txt