Metadata-Version: 2.1
Name: ebookonix
Version: 0.6
Summary: ONIX XML for zero-cost e-books
Home-page: UNKNOWN
Author: Silas S. Brown
Author-email: ssb22@cam.ac.uk
License: Apache 2
Platform: any
Classifier: Programming Language :: Python :: 3
Classifier: License :: OSI Approved :: Apache Software License
Classifier: Operating System :: OS Independent
Requires-Python: >=3.8
License-File: LICENSE
